odoo8_addon_travel-8.0.1.0.0-py2.7-nspkg.pth
odoo_addons/travel/__openerp__.py
odoo_addons/travel/__init__.py
odoo_addons/travel/security/travel_security.xml
odoo_addons/travel/security/ir.model.access.csv
odoo_addons/travel/models/res_config.py
odoo_addons/travel/models/__init__.py
odoo_addons/travel/models/travel_passenger.py
odoo_addons/travel/models/travel.py
odoo_addons/travel/i18n/travel.pot
odoo_addons/travel/i18n/fr.po
odoo_addons/travel/views/travel_passenger.xml
odoo_addons/travel/views/travel.xml
odoo_addons/travel/views/res_config.xml
odoo_addons/travel/tests/test_passenger.py
odoo_addons/travel/tests/test_res_config.py
odoo_addons/travel/tests/test_travel.py
odoo_addons/travel/tests/__init__.py
odoo_addons/travel/demo/travel.xml
odoo8_addon_travel-8.0.1.0.0.dist-info/top_level.txt
odoo8_addon_travel-8.0.1.0.0.dist-info/WHEEL
odoo8_addon_travel-8.0.1.0.0.dist-info/RECORD
odoo8_addon_travel-8.0.1.0.0.dist-info/metadata.json
odoo8_addon_travel-8.0.1.0.0.dist-info/DESCRIPTION.rst
odoo8_addon_travel-8.0.1.0.0.dist-info/METADATA
odoo8_addon_travel-8.0.1.0.0.dist-info/namespace_packages.txt
